LICENSE
MANIFEST.in
README.md
setup.cfg
setup.py
pytlv/TLV.py
pytlv/__init__.py
pytlv/tests.py
pytlv.egg-info/PKG-INFO
pytlv.egg-info/SOURCES.txt
pytlv.egg-info/dependency_links.txt
pytlv.egg-info/top_level.txt
pytlv.egg-info/zip-safe