Metadata-Version: 1.1
Name: pytlv
Version: 0.71
Summary: TLV(tag length lavue) data parser, especially useful for EMV tags parsing
Home-page: https://github.com/timgabets/pytlv
Author: Tim Gabets
Author-email: tim@gabets.ru
License: LGPLv2
Keywords: EMV TLV ICC parse
Platform: UNKNOWN
Classifier: License :: OSI Approved :: GNU Lesser General Public License v2 (LGPLv2)
Classifier: Operating System :: OS Independent
Classifier: Programming Language :: Python :: 3
Classifier: Programming Language :: Python :: 3.3
Classifier: Programming Language :: Python :: 3.4
Classifier: Programming Language :: Python :: 3.5
Classifier: Topic :: Communications
Classifier: Intended Audience :: Developers
